plex_generate_previews/__init__.py
plex_generate_previews/__main__.py
plex_generate_previews/_version.py
plex_generate_previews/cli.py
plex_generate_previews/config.py
plex_generate_previews/gpu_detection.py
plex_generate_previews/logging_config.py
plex_generate_previews/media_processing.py
plex_generate_previews/plex_client.py
plex_generate_previews/utils.py
plex_generate_previews/version_check.py
plex_generate_previews/worker.py
plex_generate_previews/fixtures/test_video.mp4
plex_generate_previews-2.7.4.dist-info/licenses/LICENSE
plex_generate_previews-2.7.4.dist-info/METADATA
plex_generate_previews-2.7.4.dist-info/WHEEL
plex_generate_previews-2.7.4.dist-info/entry_points.txt
plex_generate_previews-2.7.4.dist-info/top_level.txt
plex_generate_previews-2.7.4.dist-info/RECORD
