Metadata-Version: 2.4
Name: plex-generate-previews
Version: 2.7.4
Summary: Generate video preview thumbnails for Plex Media Server
Author-email: stevezau <stevezau@example.com>
License-Expression: MIT
Project-URL: Homepage, https://github.com/stevezau/plex_generate_vid_previews
Project-URL: Repository, https://github.com/stevezau/plex_generate_vid_previews
Project-URL: Issues, https://github.com/stevezau/plex_generate_vid_previews/issues
Keywords: plex,media,server,video,thumbnails,previews,ffmpeg,gpu,acceleration
Classifier: Development Status :: 4 - Beta
Classifier: Intended Audience :: End Users/Desktop
Classifier: Operating System :: POSIX :: Linux
Classifier: Operating System :: Microsoft :: Windows
Classifier: Operating System :: MacOS
Classifier: Programming Language :: Python :: 3
Classifier: Programming Language :: Python :: 3.7
Classifier: Programming Language :: Python :: 3.8
Classifier: Programming Language :: Python :: 3.9
Classifier: Programming Language :: Python :: 3.10
Classifier: Programming Language :: Python :: 3.11
Classifier: Topic :: Multimedia :: Video
Classifier: Topic :: System :: Archiving
Requires-Python: >=3.7
License-File: LICENSE
Requires-Dist: requests==2.32.3
Requires-Dist: urllib3<3.0.0,>=1.26.0
Requires-Dist: python-dotenv==1.1.1
Requires-Dist: plexapi==4.17.1
Requires-Dist: loguru==0.7.3
Requires-Dist: rich==13.8.1
Requires-Dist: pymediainfo==7.0.1
Requires-Dist: psutil<6.0.0,>=5.9.0
Provides-Extra: nvidia
Requires-Dist: pynvml==11.6.0; extra == "nvidia"
Provides-Extra: amd
Requires-Dist: amdsmi==6.2.1; extra == "amd"
Provides-Extra: test
Requires-Dist: pytest>=7.0.0; extra == "test"
Requires-Dist: pytest-cov>=4.0.0; extra == "test"
Requires-Dist: pytest-mock>=3.10.0; extra == "test"
Requires-Dist: pytest-xdist>=3.0.0; extra == "test"
Dynamic: license-file
